vortex_engine/Data.py
vortex_engine/Tool.py
vortex_engine/Vortex.py
vortex_engine/__init__.py
vortex_engine-0.1.6.dist-info/LICENSE
vortex_engine-0.1.6.dist-info/METADATA
vortex_engine-0.1.6.dist-info/WHEEL
vortex_engine-0.1.6.dist-info/top_level.txt
vortex_engine-0.1.6.dist-info/RECORD
