Metadata-Version: 2.1
Name: vortex-engine
Version: 0.1.6
Summary: Vortex Engine is a game engine built with Ursina for creating on-chain 2D and 3D games. It integrates with the Aptos blockchain, with plans to support Polygon, offering seamless blockchain features like transaction history within the game.
Home-page: https://github.com/HHGoa/VortexEngine.git
Author: Manikandan05
Author-email: manicdon7@gmail.com
Classifier: Programming Language :: Python :: 3
Classifier: License :: OSI Approved :: MIT License
Classifier: Operating System :: OS Independent
Requires-Python: >=3.6
License-File: LICENSE
Requires-Dist: ursina
Requires-Dist: requests
